metricgrabber/__init__.py
metricgrabber/category.py
metricgrabber/metric.py
metricgrabber/metricgrabber.py
metricgrabber-0.1.dist-info/METADATA
metricgrabber-0.1.dist-info/WHEEL
metricgrabber-0.1.dist-info/top_level.txt
metricgrabber-0.1.dist-info/RECORD
